stathub.py
stathub-0.1.4.3.dist-info/METADATA
stathub-0.1.4.3.dist-info/WHEEL
stathub-0.1.4.3.dist-info/top_level.txt
stathub-0.1.4.3.dist-info/RECORD
