Metadata-Version: 2.1
Name: stathub
Version: 0.1.4.3
Summary: A python package used for getting data from Statistics Sharing Hub.
Home-page: https://pypi.org/project/stathub
Author: Government Strategic Information Center​
Author-email: sdmx.tnso@gmail.com
Requires-Python: >=3.8
Requires-Dist: pandas
Requires-Dist: requests
Requires-Dist: openpyxl
